pymongo_crud_use/__init__.py
pymongo_crud_use/mongo_functions.py
pymongo_crud_use-0.6.1.dist-info/LICENSE
pymongo_crud_use-0.6.1.dist-info/METADATA
pymongo_crud_use-0.6.1.dist-info/WHEEL
pymongo_crud_use-0.6.1.dist-info/entry_points.txt
pymongo_crud_use-0.6.1.dist-info/top_level.txt
pymongo_crud_use-0.6.1.dist-info/RECORD
