Metadata-Version: 2.1
Name: pymongo_crud_use
Version: 0.6.1
Summary: A package for MongoDB CRUD operations using PyMongo
Home-page: https://github.com/hecdelatorre/pymongo_crud_use.git
Author: Your Name
Author-email: your.email@example.com
License: GPL-3.0
License-File: LICENSE
Requires-Dist: pymongo
Requires-Dist: pymongo[srv]
Requires-Dist: uuid7
